README.txt
setup.cfg
setup.py
Products/__init__.py
Products/__init__.pyc
Products.TemplateCacheManager.egg-info/PKG-INFO
Products.TemplateCacheManager.egg-info/SOURCES.txt
Products.TemplateCacheManager.egg-info/dependency_links.txt
Products.TemplateCacheManager.egg-info/entry_points.txt
Products.TemplateCacheManager.egg-info/namespace_packages.txt
Products.TemplateCacheManager.egg-info/not-zip-safe
Products.TemplateCacheManager.egg-info/requires.txt
Products.TemplateCacheManager.egg-info/top_level.txt
Products/TemplateCacheManager/AUTHORS.txt
Products/TemplateCacheManager/PageCache.py
Products/TemplateCacheManager/TemplateCacheManager.py
Products/TemplateCacheManager/__init__.py
Products/TemplateCacheManager/cache.gif
Products/TemplateCacheManager/interfaces.py
Products/TemplateCacheManager/version.txt
Products/TemplateCacheManager/Extensions/utils.py
Products/TemplateCacheManager/examples/INSTALL.txt
Products/TemplateCacheManager/examples/getETag.py
Products/TemplateCacheManager/www/addTCM.zpt
Products/TemplateCacheManager/www/editTCM.zpt
Products/TemplateCacheManager/www/statsTCM.zpt
docs/HISTORY.txt
docs/INSTALL.txt
docs/LICENSE.txt
