Metadata-Version: 1.0
Name: Products.TemplateCacheManager
Version: 0.1dev-r67816
Summary: Cache rendered pages including headers with ETag support
Home-page: http://svn.plone.org/svn/collective/Products.TemplateCacheManager
Author: Andreas Gabriel
Author-email: gabriel@hrz.uni-marbug.de
License: ZPL
Keywords: caching zope CMF
Platform: UNKNOWN
Classifier: Framework :: Plone
Classifier: Programming Language :: Python
Classifier: Topic :: Software Development :: Libraries :: Python Modules
